[
  {
    "title": "Eli Tea Bar",
    "url": "https://www.eliteabar.com/",
    "image": "https://lh3.googleusercontent.com/p/AF1QipNr0vg5BuTYohcGwRhOb-HU1V6HRZebxm7ww5m2=s680-w680-h510",
    "location": ["Chicago, IL"],
    "type": ["Space"],
    "identity": [],
    "time": ["Morning", "Afternoon", "Evening"],
    "vibe": ["Dry Bar"]
  },
  {
    "title": "Anne's Haven",
    "url": "http://www.anneshaven.net/",
    "image": "https://lh3.googleusercontent.com/p/AF1QipP0W-Z0oAalWVIDtNi4EG3Rvuxq8J6h0KzITrXB=s680-w680-h510",
    "location": ["Chicago, IL"],
    "type": ["Group", "Space"],
    "identity": ["Lesbian"],
    "time": ["Morning", "Afternoon", "Evening"],
    "vibe": []
  },
  {
    "title": "Bendición Dry Bar",
    "url": "https://www.instagram.com/bendicion_bottleshop/?hl=en",
    "image": "https://i0.wp.com/bcc-newspack.s3.amazonaws.com/uploads/2022/11/bottle-shop.jpg?fit=780%2C544&ssl=1",
    "location": ["Chicago, IL"],
    "type": ["Space"],
    "identity": [],
    "time": ["Morning", "Afternoon", "Evening"],
    "vibe": ["Dry Bar"]
  },
  {
    "title": "The Brown Elephant",
    "url": "https://howardbrown.org/get-involved/brown-elephant/",
    "image": "https://www.yelp.com/biz_photos/brown-elephant-resale-shop-chicago?select=X2bcn3w3P_D21O0XpM6W8w",
    "location": ["Chicago, IL"],
    "type": ["Space"],
    "identity": [],
    "time": ["Morning", "Afternoon", "Evening"],
    "vibe": []
  },
  {
    "title": "Chicago Queer Contra",
    "url": "https://chicagoqueercontra.wordpress.com/",
    "image": "https://chicagoqueercontra.wordpress.com/wp-content/uploads/2017/03/queer-contra-3.jpg?w=2000&h=1200&crop=1",
    "location": ["Chicago, IL"],
    "type": ["Group"],
    "identity": [],
    "time": ["Morning", "Afternoon", "Evening"],
    "vibe": []
  },
  {
    "title": "Lez Get Together",
    "url": "https://linktr.ee/lezgetogether",
    "image": "https://i0.wp.com/bcc-newspack.s3.amazonaws.com/uploads/2023/03/IMG_6420-1.jpg?fit=780%2C439&ssl=1",
    "location": ["Chicago, IL"],
    "type": ["Group"],
    "identity": ["Lesbian"],
    "time": ["Morning", "Afternoon", "Evening"],
    "vibe": []
  },
  {
    "title": "Full Moon Jam",
    "url": "https://www.fullmoonjam.org/",
    "image": "https://i0.wp.com/chicagoonthecheap.com/lotc-cms/wp-content/uploads/firejam.jpeg?w=600&ssl=1",
    "location": ["Chicago, IL"],
    "type": ["Event"],
    "identity": [],
    "time": ["Evening"],
    "vibe": ["Outdoor", "Family-Friendly"]
  },
  {
    "title": "Leather Archives & Museum",
    "url": "https://www.choosechicago.com/listing/leather-archives-museum/",
    "image": "https://chicago.simpleviewcrm.com/images/listings/IMG_69250.jpg",
    "location": ["Chicago, IL"],
    "type": ["Space"],
    "identity": [],
    "time": ["Morning", "Afternoon", "Evening"],
    "vibe": ["Kink (18+)"]
  }
]
